devpro_s3_storages/__init__.py
devpro_s3_storages/handlers.py
devpro_s3_storages-0.2.0.dist-info/LICENSE
devpro_s3_storages-0.2.0.dist-info/METADATA
devpro_s3_storages-0.2.0.dist-info/WHEEL
devpro_s3_storages-0.2.0.dist-info/RECORD
